{
    "id": "f7040e",
    "creted_at": "2025-05-05 23:07:02",
    "operations": [
        {
            "schema_name": "employees",
            "table_name": "department",
            "operation": "update",
            "columns": [
                {
                    "name": "id",
                    "type": "character",
                    "value": "d009"
                },
                {
                    "name": "dept_name",
                    "type": "character varying",
                    "value": "Customers Relationship"
                }
            ]
        }
    ]
}